<?xml version="1.0" encoding="UTF-8"?>
<ruleset name="Java Rules with Cyclomatic Complexity"
    xmlns="http://pmd.sourceforge.net/ruleset/2.0.0"
    xmlns:xsi="http://www.w3.org/2001/XMLSchema-instance"
    xsi:schemaLocation="http://pmd.sourceforge.net/ruleset/2.0.0 https://pmd.sourceforge.io/ruleset_2_0_0.xsd">
    <description>PMD Java ruleset including CyclomaticComplexity rule with default configuration</description>

    <!-- Cyclomatic Complexity Rule -->
    <rule ref="category/java/design.xml/CyclomaticComplexity">
        <properties>
            <property name="methodReportLevel" value="7" />
            <property name="classReportLevel" value="80" />
        </properties>
    </rule>

</ruleset>
